tmdl/__init__.py
tmdl/dump.py
tmdl/load.py
tmdl/models/__init__.py
tmdl/models/column.py
tmdl/models/database.py
tmdl/models/model.py
tmdl/models/partition.py
tmdl/models/relationship.py
tmdl/models/table.py
tmdl/parsers/__init__.py
tmdl/parsers/base.py
tmdl/parsers/column.py
tmdl/parsers/partition.py
tmdl/parsers/table.py
pytmdl-0.1.1a1.dist-info/METADATA
pytmdl-0.1.1a1.dist-info/WHEEL
pytmdl-0.1.1a1.dist-info/RECORD
